docs/source/conf.py
examples/WBGTLijigrennew.py
examples/compute-obs.py
examples/compute-thermal-indices.py
examples/mplot.py
examples/numerical-ingration-cossza.py
examples/thermofeelexamplesourcecode1.py
tests/test_scalars.py
tests/test_thermofeel.py
thermofeel/__init__.py
thermofeel/experimental_wbgt.py
thermofeel/helpers.py
thermofeel/thermofeel.py
thermofeel-2.1.4.dist-info/licenses/LICENSE
thermofeel-2.1.4.dist-info/METADATA
thermofeel-2.1.4.dist-info/WHEEL
thermofeel-2.1.4.dist-info/top_level.txt
thermofeel-2.1.4.dist-info/zip-safe
thermofeel-2.1.4.dist-info/RECORD
